pyspacelog/__init__.py
pyspacelog/main.py
pyspacelog-0.0.11.dist-info/METADATA
pyspacelog-0.0.11.dist-info/WHEEL
pyspacelog-0.0.11.dist-info/top_level.txt
pyspacelog-0.0.11.dist-info/RECORD
