Metadata-Version: 2.1
Name: pyspacelog
Version: 0.0.11
Author: Arbit
Author-email: 
License: MIT
Requires-Dist: requests
